CHANGELOG.txt
LICENSE.txt
MANIFEST.in
README.txt
setup.py
.ipynb_checkpoints/CHANGELOG-checkpoint.txt
.ipynb_checkpoints/LICENSE-checkpoint.txt
.ipynb_checkpoints/README-checkpoint.txt
.ipynb_checkpoints/setup-checkpoint.py
skyiris/__init__.py
skyiris.egg-info/PKG-INFO
skyiris.egg-info/SOURCES.txt
skyiris.egg-info/dependency_links.txt
skyiris.egg-info/top_level.txt
skyiris/.ipynb_checkpoints/__init__-checkpoint.py
skyiris/.ipynb_checkpoints/setup-checkpoint.py