Metadata-Version: 1.1
Name: skyiris
Version: 0.1.3
Summary: machine leanring with iris_dataset
Home-page: UNKNOWN
Author: SkyKang
Author-email: godsky@naver.com
License: MIT
Keywords: skyiris
Platform: UNKNOWN
Classifier: Development Status :: 5 - Production/Stable
Classifier: Intended Audience :: Education
Classifier: Operating System :: Microsoft :: Windows :: Windows 10
Classifier: License :: OSI Approved :: MIT License
Classifier: Programming Language :: Python :: 3
